armored/__base.py
armored/__init__.py
armored/__main__.py
armored/__types.py
armored/cli.py
armored/conn.py
armored/const.py
armored/dtype.py
armored/lineage.py
armored/settings.py
armored/trans.py
armored/utils.py
armored/datasets/__init__.py
armored/datasets/col.py
armored/datasets/db.py
armored/datasets/file.py
armored/enums/__init__.py
armored/enums/status.py
armored-0.0.3.dist-info/entry_points.txt
armored-0.0.3.dist-info/LICENSE
armored-0.0.3.dist-info/WHEEL
armored-0.0.3.dist-info/METADATA
armored-0.0.3.dist-info/RECORD
