Metadata-Version: 2.1
Name: armored
Version: 0.0.3
Summary: Armored that implements Model objects for Data Pipeline
Keywords: models,armored
Maintainer-email: korawica <korawich.anu@gmail.com>
Requires-Python: >=3.9.0
Classifier: Topic :: Utilities
Classifier: Natural Language :: English
Classifier: Development Status :: 4 - Beta
Classifier: Operating System :: OS Independent
Classifier: Programming Language :: Python
Classifier: Programming Language :: Python :: 3 :: Only
Classifier: Programming Language :: Python :: 3.9
Classifier: Programming Language :: Python :: 3.10
Classifier: Programming Language :: Python :: 3.11
Classifier: Programming Language :: Python :: 3.12
Requires-Dist: tzdata
Requires-Dist: pydantic==2.6.0
Requires-Dist: clishelf ; extra == "test"
Project-URL: Homepage, https://github.com/korawica/armored/
Project-URL: Source Code, https://github.com/korawica/armored/
Provides-Extra: test
